txssmi/__init__.py
txssmi/builder.py
txssmi/commands.py
txssmi/constants.py
txssmi/protocol.py
txssmi/tests/__init__.py
txssmi/tests/test_commands.py
txssmi/tests/test_protocol.py
txssmi-0.3.0.dist-info/DESCRIPTION.rst
txssmi-0.3.0.dist-info/METADATA
txssmi-0.3.0.dist-info/metadata.json
txssmi-0.3.0.dist-info/RECORD
txssmi-0.3.0.dist-info/top_level.txt
txssmi-0.3.0.dist-info/WHEEL
