Metadata-Version: 2.0
Name: txssmi
Version: 0.3.0
Summary: Twisted library for Truteq's SSMI protocol
Home-page: http://github.com/smn/txssmi
Author: Simon de Haan
Author-email: simon@praekeltfoundation.org
License: BSD
Platform: UNKNOWN
Classifier: Development Status :: 3 - Alpha
Classifier: Intended Audience :: Developers
Classifier: License :: OSI Approved :: BSD License
Classifier: Operating System :: POSIX
Classifier: Programming Language :: Python
Classifier: Topic :: Software Development :: Libraries :: Python Modules
Classifier: Topic :: System :: Networking
Classifier: Framework :: Twisted
Requires-Dist: Twisted
